odoo8_addon_product_supplierinfo_tree_price_info-8.0.0.1.0-py2.7-nspkg.pth
odoo8_addon_product_supplierinfo_tree_price_info-8.0.0.1.0.dist-info/top_level.txt
odoo8_addon_product_supplierinfo_tree_price_info-8.0.0.1.0.dist-info/WHEEL
odoo8_addon_product_supplierinfo_tree_price_info-8.0.0.1.0.dist-info/RECORD
odoo8_addon_product_supplierinfo_tree_price_info-8.0.0.1.0.dist-info/metadata.json
odoo8_addon_product_supplierinfo_tree_price_info-8.0.0.1.0.dist-info/DESCRIPTION.rst
odoo8_addon_product_supplierinfo_tree_price_info-8.0.0.1.0.dist-info/METADATA
odoo8_addon_product_supplierinfo_tree_price_info-8.0.0.1.0.dist-info/namespace_packages.txt
odoo_addons/product_supplierinfo_tree_price_info/__openerp__.py
odoo_addons/product_supplierinfo_tree_price_info/__init__.py
odoo_addons/product_supplierinfo_tree_price_info/README.rst
odoo_addons/product_supplierinfo_tree_price_info/models/__init__.py
odoo_addons/product_supplierinfo_tree_price_info/models/product_supplierinfo.py
odoo_addons/product_supplierinfo_tree_price_info/i18n/es.po
odoo_addons/product_supplierinfo_tree_price_info/i18n/product_with_supplier_unit_price.pot
odoo_addons/product_supplierinfo_tree_price_info/i18n/fr.po
odoo_addons/product_supplierinfo_tree_price_info/views/product_supplierinfo.xml
odoo_addons/product_supplierinfo_tree_price_info/demo/res_groups.yml
odoo_addons/product_supplierinfo_tree_price_info/demo/product_template.yml
odoo_addons/product_supplierinfo_tree_price_info/static/description/screenshot.png
odoo_addons/product_supplierinfo_tree_price_info/static/description/icon.png
